{"hardpoints":[{"type":12,"position":[2,6],"shape":{"name":[[true,true],[true,true]]},"transform":null,"rotation":0,"armor":50.0},{"type":13,"position":[2,3],"shape":{"name":[[true,true],[true,true]]},"transform":"Drive","rotation":0,"armor":10.0},{"type":9,"position":[1,8],"shape":{"name":[[true,true]]},"transform":"En.L","rotation":0,"armor":20.0},{"type":9,"position":[4,8],"shape":{"name":[[true,true]]},"transform":"En.R","rotation":0,"armor":20.0},{"type":11,"position":[0,5],"shape":{"name":[[true,true,true]]},"transform":"La.L","rotation":0,"armor":30.0},{"type":11,"position":[5,5],"shape":{"name":[[true,true,true]]},"transform":"La.R","rotation":0,"armor":30.0},{"type":6,"position":[1,2],"shape":{"name":[[true,true]]},"transform":"Ra.L","rotation":1,"armor":10.0},{"type":6,"position":[4,2],"shape":{"name":[[true,true]]},"transform":"Ra.R","rotation":3,"armor":10.0},{"type":5,"position":[2,1],"shape":{"name":[[true,true],[true,true]]},"transform":"Reactor","rotation":0,"armor":0.0},{"type":8,"position":[3,10],"shape":{"name":[[true]]},"transform":null,"rotation":0,"armor":5.0}],"prefab":"Assets/Resources/Prefabs/Ships/Longinus.prefab","hullType":0,"gridOffset":3.0,"armor":10.0,"drag":0.1,"canTow":false,"schematic":"Assets/Resources/Schematics/schema_Longinus.png","behaviors":[{"crossSection":{"min":500.0,"max":150.0,"heatExponentMultiplier":0.0,"durabilityExponentMultiplier":1.0,"qualityExponent":2.0},"group":0,"$type":"ReflectorData"}],"durability":500.0,"minTemp":173.15,"maxTemp":573.15,"heatCurve":{"keys":[[0.0,0.0,8.389394,8.389394],[0.357228935,0.8660065,-2.46956825,-2.46956825],[1.0,0.0,-0.6179685,-0.6179685]]},"resilience":1.0,"actionIcon":"","soundBank":85412153,"audioStats":[],"name":"LonginusX","description":null,"creator":"a1f76631-d6d1-443a-9be1-c9b1267d6ca2","mass":2500.0,"shape":{"name":[[false,false,false,false,true,true,true,true,true,false,false,false,false,false,false,false,false],[true,true,true,true,true,true,true,true,true,true,true,false,false,false,false,false,false],[true,true,true,true,true,true,true,true,true,true,true,true,true,true,true,true,true],[true,true,true,true,true,true,true,true,true,true,true,true,true,true,true,true,true],[true,true,true,true,true,true,true,true,true,true,true,false,false,false,false,false,false],[false,false,false,false,true,true,true,true,true,false,false,false,false,false,false,false,false]]},"specificHeat":1.0,"conductivity":32.0,"price":7500000,"id":"445d911a-9951-40a3-874e-0b7ce8b35129","$type":"HullData"}